bintrace/__init__.py
bintrace-0.1.0.dist-info/METADATA
bintrace-0.1.0.dist-info/WHEEL
bintrace-0.1.0.dist-info/top_level.txt
bintrace-0.1.0.dist-info/RECORD
